federated_search/__init__.py
federated_search/contextual_pgvector.py
federated_search/interfaces.py
federated_search/reranker.py
federated_search-0.1.1.dist-info/METADATA
federated_search-0.1.1.dist-info/WHEEL
federated_search-0.1.1.dist-info/top_level.txt
federated_search-0.1.1.dist-info/RECORD
